t_log/__init__.py
t_log/logger.py
t_log-0.52.dist-info/LICENSE
t_log-0.52.dist-info/METADATA
t_log-0.52.dist-info/WHEEL
t_log-0.52.dist-info/top_level.txt
t_log-0.52.dist-info/RECORD
