Metadata-Version: 2.1
Name: t-log
Version: 0.52
Summary: A small log package
Home-page: https://github.com/Tinywan/t_log
Author: Tinywan
Author-email: 756684177@qq.com
License: UNKNOWN
Platform: UNKNOWN
Classifier: Programming Language :: Python :: 3
Classifier: License :: OSI Approved :: MIT License
Classifier: Operating System :: OS Independent
